davis_summary_vac/__init__.py
davis_summary_vac/analyzer.py
davis_summary_vac-0.2.0.dist-info/LICENSE
davis_summary_vac-0.2.0.dist-info/METADATA
davis_summary_vac-0.2.0.dist-info/WHEEL
davis_summary_vac-0.2.0.dist-info/entry_points.txt
davis_summary_vac-0.2.0.dist-info/top_level.txt
davis_summary_vac-0.2.0.dist-info/RECORD
