Metadata-Version: 2.1
Name: davis_summary_vac
Version: 0.2.0
Summary: A package for analyzing CSV files and generating summary reports in HTML
Home-page: https://github.com/Wearevac/davis-summary
Author: Niranjan Gopalan
Author-email: niranjangopalan948@gmail.com
License: MIT
Classifier: Programming Language :: Python :: 3
Classifier: License :: OSI Approved :: MIT License
Classifier: Operating System :: OS Independent
Requires-Python: >=3.6
License-File: LICENSE
Requires-Dist: matplotlib
Requires-Dist: seaborn
Requires-Dist: pandas
Requires-Dist: statistics
